hello_world/__init__.py
hello_world/main.py
hello_world_ericjaychi22-0.0.4.dist-info/LICENSE
hello_world_ericjaychi22-0.0.4.dist-info/METADATA
hello_world_ericjaychi22-0.0.4.dist-info/WHEEL
hello_world_ericjaychi22-0.0.4.dist-info/top_level.txt
hello_world_ericjaychi22-0.0.4.dist-info/RECORD
