Metadata-Version: 2.1
Name: hello-world-ericjaychi22
Version: 0.0.4
Summary: A Hello World package
Home-page: https://github.com/ericjaychi/sample-pypi-package
Author: Eric Chi
Author-email: ericjaychi@gmail.com
License: UNKNOWN
Platform: UNKNOWN
Classifier: Programming Language :: Python :: 3.8
Classifier: License :: OSI Approved :: MIT License
Classifier: Operating System :: OS Independent
Requires-Python: >=3.6
Requires-Dist: requests (<=2.21.0)
Requires-Dist: django (<=3.0.8)
